{
  "scenario": "full_tariff_reallocation_lag3",
  "n_draws": 20,
  "exchequer_cost_mean": 442458112.0,
  "exchequer_cost_sd": 127874244.77150644,
  "poverty_rate_change_bhc_mean": 8.758050131980056e-05,
  "poverty_rate_change_bhc_sd": 7.721796201388017e-05,
  "gini_change_mean": 5.813753813149747e-06,
  "gini_change_sd": 8.827604285200837e-05,
  "displaced_weighted_mean": 0.0,
  "lcwra_weighted_mean": 0.0,
  "reallocated_weighted_mean": 33565.60322265625,
  "cushioning_rate_mean": 0.37946249680569716,
  "cushioning_rate_sd": 0.0298142243775571,
  "draws": [
    {
      "scenario": "full_tariff_reallocation_lag3",
      "tariff_scenario": "full_tariff",
      "margin": "reallocation",
      "exchequer_cost": 398491648.0,
      "poverty_rate_change_bhc": 4.338921517471617e-05,
      "poverty_rate_change_ahc": 9.611983319682271e-05,
      "absolute_poverty_rate_change_bhc": NaN,
      "gini_baseline": 0.30908967456288927,
      "gini_shocked": 0.30915515396520243,
      "displaced_weighted": 0.0,
      "inactive_weighted": 0.0,
      "lcwra_weighted": 0.0,
      "reallocated_weighted": 35003.78515625,
      "gross_earnings_loss": 786315342.615799,
      "net_disposable_loss": 502661120.0,
      "cushioning_rate": 0.3607385068593213,
      "decile_income_change": {
        "1": -21.957319259643555,
        "2": 0.0,
        "3": -3.833170175552368,
        "4": -17.46341896057129,
        "5": -22.930910110473633,
        "6": -8.583396911621094,
        "7": -16.742834091186523,
        "8": -42.690006256103516,
        "9": -39.62176513671875,
        "10": -44.567230224609375
      },
      "region_income_change": {
        "EAST_MIDLANDS": -87.1939926147461,
        "EAST_OF_ENGLAND": -21.087154388427734,
        "LONDON": -25.559846878051758,
        "NORTHERN_IRELAND": -4.627901554107666,
        "NORTH_EAST": 0.0,
        "NORTH_WEST": -13.870589256286621,
        "SCOTLAND": -45.6277961730957,
        "SOUTH_EAST": -3.2499358654022217,
        "SOUTH_WEST": -14.374391555786133,
        "WALES": -15.226771354675293,
        "WEST_MIDLANDS": -27.79287338256836,
        "YORKSHIRE": 0.0
      },
      "age_band_displacement_share": {
        "16-24": 0.0,
        "25-34": 0.2295939177274704,
        "35-44": 0.25983479619026184,
        "45-54": 0.17844147980213165,
        "55-64": 0.29160651564598083,
        "65-+": 0.04052337259054184
      }
    },
    {
      "scenario": "full_tariff_reallocation_lag3",
      "tariff_scenario": "full_tariff",
      "margin": "reallocation",
      "exchequer_cost": 395968512.0,
      "poverty_rate_change_bhc": 5.820661527577986e-05,
      "poverty_rate_change_ahc": 6.481002046862527e-05,
      "absolute_poverty_rate_change_bhc": NaN,
      "gini_baseline": 0.30908967456288927,
      "gini_shocked": 0.3090280472493492,
      "displaced_weighted": 0.0,
      "inactive_weighted": 0.0,
      "lcwra_weighted": 0.0,
      "reallocated_weighted": 31450.029296875,
      "gross_earnings_loss": 789385169.6567116,
      "net_disposable_loss": 506331136.0,
      "cushioning_rate": 0.3585753122012747,
      "decile_income_change": {
        "1": -0.6777105927467346,
        "2": 0.0,
        "3": -0.9168550372123718,
        "4": 0.0,
        "5": -17.380985260009766,
        "6": -25.87567710876465,
        "7": -17.11363983154297,
        "8": -23.03543472290039,
        "9": -3.367913007736206,
        "10": -87.25820922851562
      },
      "region_income_change": {
        "EAST_MIDLANDS": -10.53411865234375,
        "EAST_OF_ENGLAND": -23.65043067932129,
        "LONDON": -28.702600479125977,
        "NORTHERN_IRELAND": -37.64664840698242,
        "NORTH_EAST": -46.07201385498047,
        "NORTH_WEST": 0.0,
        "SCOTLAND": -51.668880462646484,
        "SOUTH_EAST": -2.4953553676605225,
        "SOUTH_WEST": 0.0,
        "WALES": -5.797136306762695,
        "WEST_MIDLANDS": -19.822641372680664,
        "YORKSHIRE": -15.28589916229248
      },
      "age_band_displacement_share": {
        "16-24": 0.0,
        "25-34": 0.21477478742599487,
        "35-44": 0.06419776380062103,
        "45-54": 0.3109589219093323,
        "55-64": 0.3453885018825531,
        "65-+": 0.06467997282743454
      }
    },
    {
      "scenario": "full_tariff_reallocation_lag3",
      "tariff_scenario": "full_tariff",
      "margin": "reallocation",
      "exchequer_cost": 235241472.0,
      "poverty_rate_change_bhc": 5.3310429152853e-05,
      "poverty_rate_change_ahc": 7.505335433444227e-05,
      "absolute_poverty_rate_change_bhc": NaN,
      "gini_baseline": 0.30908967456288927,
      "gini_shocked": 0.30921133139102164,
      "displaced_weighted": 0.0,
      "inactive_weighted": 0.0,
      "lcwra_weighted": 0.0,
      "reallocated_weighted": 31046.626953125,
      "gross_earnings_loss": 497219880.06420165,
      "net_disposable_loss": 336461824.0,
      "cushioning_rate": 0.3233138144907729,
      "decile_income_change": {
        "1": -6.633004665374756,
        "2": 0.0,
        "3": -17.882905960083008,
        "4": -19.051828384399414,
        "5": -53.3315544128418,
        "6": -6.230615139007568,
        "7": -34.099735260009766,
        "8": -16.72318458557129,
        "9": 0.0,
        "10": -8.814359664916992
      },
      "region_income_change": {
        "EAST_MIDLANDS": -10.128011703491211,
        "EAST_OF_ENGLAND": -32.38072204589844,
        "LONDON": -5.578660488128662,
        "NORTHERN_IRELAND": -25.70416259765625,
        "NORTH_EAST": 0.0,
        "NORTH_WEST": -19.3759822845459,
        "SCOTLAND": -27.393339157104492,
        "SOUTH_EAST": -6.578042507171631,
        "SOUTH_WEST": -18.66428565979004,
        "WALES": -12.851961135864258,
        "WEST_MIDLANDS": -15.42133903503418,
        "YORKSHIRE": -25.18766212463379
      },
      "age_band_displacement_share": {
        "16-24": 0.143936425447464,
        "25-34": 0.12084799259901047,
        "35-44": 0.3217402696609497,
        "45-54": 0.3044809103012085,
        "55-64": 0.10899440944194794,
        "65-+": 0.0
      }
    },
    {
      "scenario": "full_tariff_reallocation_lag3",
      "tariff_scenario": "full_tariff",
      "margin": "reallocation",
      "exchequer_cost": 513671168.0,
      "poverty_rate_change_bhc": 0.0002077818342973714,
      "poverty_rate_change_ahc": 7.832284747008589e-05,
      "absolute_poverty_rate_change_bhc": NaN,
      "gini_baseline": 0.30908967456288927,
      "gini_shocked": 0.3091056921060691,
      "displaced_weighted": 0.0,
      "inactive_weighted": 0.0,
      "lcwra_weighted": 0.0,
      "reallocated_weighted": 32813.90625,
      "gross_earnings_loss": 939533540.3739419,
      "net_disposable_loss": 566755328.0,
      "cushioning_rate": 0.39676945670888253,
      "decile_income_change": {
        "1": -13.461874961853027,
        "2": -23.32921028137207,
        "3": 0.0,
        "4": 0.0,
        "5": -3.2354087829589844,
        "6": -18.364944458007812,
        "7": -23.40873146057129,
        "8": -66.66572570800781,
        "9": -37.29176330566406,
        "10": -83.85099029541016
      },
      "region_income_change": {
        "EAST_MIDLANDS": -90.99826049804688,
        "EAST_OF_ENGLAND": -67.65714263916016,
        "LONDON": -35.84552001953125,
        "NORTHERN_IRELAND": -18.000486373901367,
        "NORTH_EAST": 0.0,
        "NORTH_WEST": 0.0,
        "SCOTLAND": -14.743256568908691,
        "SOUTH_EAST": -34.53538513183594,
        "SOUTH_WEST": -8.525439262390137,
        "WALES": -28.396726608276367,
        "WEST_MIDLANDS": 0.0,
        "YORKSHIRE": -14.908125877380371
      },
      "age_band_displacement_share": {
        "16-24": 0.053364552557468414,
        "25-34": 0.23129773139953613,
        "35-44": 0.42106232047080994,
        "45-54": 0.20236624777317047,
        "55-64": 0.09190903604030609,
        "65-+": 0.0
      }
    },
    {
      "scenario": "full_tariff_reallocation_lag3",
      "tariff_scenario": "full_tariff",
      "margin": "reallocation",
      "exchequer_cost": 527155200.0,
      "poverty_rate_change_bhc": 0.0002670514332431262,
      "poverty_rate_change_ahc": 0.0002549720307965797,
      "absolute_poverty_rate_change_bhc": NaN,
      "gini_baseline": 0.30908967456288927,
      "gini_shocked": 0.3090893603671988,
      "displaced_weighted": 0.0,
      "inactive_weighted": 0.0,
      "lcwra_weighted": 0.0,
      "reallocated_weighted": 35732.7421875,
      "gross_earnings_loss": 937789941.556873,
      "net_disposable_loss": 548012032.0,
      "cushioning_rate": 0.41563455981387765,
      "decile_income_change": {
        "1": -5.138112545013428,
        "2": -15.78242015838623,
        "3": -8.797459602355957,
        "4": -1.6399624347686768,
        "5": -5.804725646972656,
        "6": -8.915691375732422,
        "7": -41.01264953613281,
        "8": -7.092154026031494,
        "9": -5.220525741577148,
        "10": -80.10899353027344
      },
      "region_income_change": {
        "EAST_MIDLANDS": -26.76067543029785,
        "EAST_OF_ENGLAND": -12.560371398925781,
        "LONDON": -4.128345012664795,
        "NORTHERN_IRELAND": -40.918312072753906,
        "NORTH_EAST": 0.0,
        "NORTH_WEST": -33.88007354736328,
        "SCOTLAND": -17.208528518676758,
        "SOUTH_EAST": -9.389751434326172,
        "SOUTH_WEST": -7.717662811279297,
        "WALES": -23.940549850463867,
        "WEST_MIDLANDS": -47.117557525634766,
        "YORKSHIRE": -11.073677062988281
      },
      "age_band_displacement_share": {
        "16-24": 0.0,
        "25-34": 0.2120080143213272,
        "35-44": 0.2306821644306183,
        "45-54": 0.35268649458885193,
        "55-64": 0.17777210474014282,
        "65-+": 0.026851143687963486
      }
    },
    {
      "scenario": "full_tariff_reallocation_lag3",
      "tariff_scenario": "full_tariff",
      "margin": "reallocation",
      "exchequer_cost": 377503744.0,
      "poverty_rate_change_bhc": 8.536110906648409e-06,
      "poverty_rate_change_ahc": 0.0,
      "absolute_poverty_rate_change_bhc": NaN,
      "gini_baseline": 0.30908967456288927,
      "gini_shocked": 0.3091349558099219,
      "displaced_weighted": 0.0,
      "inactive_weighted": 0.0,
      "lcwra_weighted": 0.0,
      "reallocated_weighted": 31607.75,
      "gross_earnings_loss": 721111692.9995326,
      "net_disposable_loss": 451805184.0,
      "cushioning_rate": 0.37346018878064036,
      "decile_income_change": {
        "1": -6.4466023445129395,
        "2": 0.0,
        "3": 0.0,
        "4": -9.239395141601562,
        "5": -4.24596643447876,
        "6": -38.5197639465332,
        "7": -19.087610244750977,
        "8": -71.90411376953125,
        "9": -47.192108154296875,
        "10": -11.410831451416016
      },
      "region_income_change": {
        "EAST_MIDLANDS": -22.214778900146484,
        "EAST_OF_ENGLAND": -62.24519348144531,
        "LONDON": -3.1506283283233643,
        "NORTHERN_IRELAND": -28.213136672973633,
        "NORTH_EAST": -10.931676864624023,
        "NORTH_WEST": -5.998083591461182,
        "SCOTLAND": -17.63428497314453,
        "SOUTH_EAST": -40.44618606567383,
        "SOUTH_WEST": -20.16617202758789,
        "WALES": -12.687204360961914,
        "WEST_MIDLANDS": -2.874819040298462,
        "YORKSHIRE": -18.079723358154297
      },
      "age_band_displacement_share": {
        "16-24": 0.04215845838189125,
        "25-34": 0.23724527657032013,
        "35-44": 0.3581230342388153,
        "45-54": 0.2601477801799774,
        "55-64": 0.1023254245519638,
        "65-+": 0.0
      }
    },
    {
      "scenario": "full_tariff_reallocation_lag3",
      "tariff_scenario": "full_tariff",
      "margin": "reallocation",
      "exchequer_cost": 437567488.0,
      "poverty_rate_change_bhc": 0.0001571127627490454,
      "poverty_rate_change_ahc": 0.00012953951388225415,
      "absolute_poverty_rate_change_bhc": NaN,
      "gini_baseline": 0.30908967456288927,
      "gini_shocked": 0.309099594189568,
      "displaced_weighted": 0.0,
      "inactive_weighted": 0.0,
      "lcwra_weighted": 0.0,
      "reallocated_weighted": 36294.875,
      "gross_earnings_loss": 818326795.9855227,
      "net_disposable_loss": 501088256.0,
      "cushioning_rate": 0.3876673005720994,
      "decile_income_change": {
        "1": 0.0,
        "2": -1.1706533432006836,
        "3": -19.267946243286133,
        "4": -1.2589048147201538,
        "5": -11.31515884399414,
        "6": -13.035863876342773,
        "7": -26.621623992919922,
        "8": -74.87554931640625,
        "9": -44.566001892089844,
        "10": -48.58372497558594
      },
      "region_income_change": {
        "EAST_MIDLANDS": -30.022729873657227,
        "EAST_OF_ENGLAND": -31.793317794799805,
        "LONDON": -4.494515895843506,
        "NORTHERN_IRELAND": -12.585077285766602,
        "NORTH_EAST": 0.0,
        "NORTH_WEST": -14.423017501831055,
        "SCOTLAND": -50.54421615600586,
        "SOUTH_EAST": -27.160808563232422,
        "SOUTH_WEST": -16.419618606567383,
        "WALES": -73.20317840576172,
        "WEST_MIDLANDS": -18.794017791748047,
        "YORKSHIRE": -20.37017059326172
      },
      "age_band_displacement_share": {
        "16-24": 0.0,
        "25-34": 0.29972976446151733,
        "35-44": 0.38023337721824646,
        "45-54": 0.1643499732017517,
        "55-64": 0.12688374519348145,
        "65-+": 0.028803030028939247
      }
    },
    {
      "scenario": "full_tariff_reallocation_lag3",
      "tariff_scenario": "full_tariff",
      "margin": "reallocation",
      "exchequer_cost": 282542080.0,
      "poverty_rate_change_bhc": 7.257305181221363e-05,
      "poverty_rate_change_ahc": 7.257305181221363e-05,
      "absolute_poverty_rate_change_bhc": NaN,
      "gini_baseline": 0.30908967456288927,
      "gini_shocked": 0.30915724160014035,
      "displaced_weighted": 0.0,
      "inactive_weighted": 0.0,
      "lcwra_weighted": 0.0,
      "reallocated_weighted": 28284.5,
      "gross_earnings_loss": 575467306.1707361,
      "net_disposable_loss": 377880576.0,
      "cushioning_rate": 0.34335005316898726,
      "decile_income_change": {
        "1": 0.0,
        "2": 0.0,
        "3": -3.354860782623291,
        "4": 0.0,
        "5": -36.9041748046875,
        "6": -22.004405975341797,
        "7": -70.45664978027344,
        "8": -5.910943031311035,
        "9": -2.3375542163848877,
        "10": -37.28049850463867
      },
      "region_income_change": {
        "EAST_MIDLANDS": -12.037647247314453,
        "EAST_OF_ENGLAND": -28.92337989807129,
        "LONDON": -4.494515895843506,
        "NORTHERN_IRELAND": -27.672719955444336,
        "NORTH_EAST": 0.0,
        "NORTH_WEST": -5.998083591461182,
        "SCOTLAND": -18.295276641845703,
        "SOUTH_EAST": -14.192646980285645,
        "SOUTH_WEST": -19.065370559692383,
        "WALES": -8.756438255310059,
        "WEST_MIDLANDS": -67.89054107666016,
        "YORKSHIRE": -12.358152389526367
      },
      "age_band_displacement_share": {
        "16-24": 0.04582499712705612,
        "25-34": 0.20671290159225464,
        "35-44": 0.3880111575126648,
        "45-54": 0.1663568913936615,
        "55-64": 0.13136260211467743,
        "65-+": 0.0617314912378788
      }
    },
    {
      "scenario": "full_tariff_reallocation_lag3",
      "tariff_scenario": "full_tariff",
      "margin": "reallocation",
      "exchequer_cost": 420773888.0,
      "poverty_rate_change_bhc": 0.00017510302371420705,
      "poverty_rate_change_ahc": 0.0001930771726567082,
      "absolute_poverty_rate_change_bhc": NaN,
      "gini_baseline": 0.30908967456288927,
      "gini_shocked": 0.30899767161186587,
      "displaced_weighted": 0.0,
      "inactive_weighted": 0.0,
      "lcwra_weighted": 0.0,
      "reallocated_weighted": 32307.37890625,
      "gross_earnings_loss": 924197760.7662549,
      "net_disposable_loss": 580386816.0,
      "cushioning_rate": 0.3720101469205036,
      "decile_income_change": {
        "1": 0.0,
        "2": -3.8758628368377686,
        "3": -16.253684997558594,
        "4": -1.217055082321167,
        "5": -6.054963111877441,
        "6": -9.264687538146973,
        "7": -43.2101936340332,
        "8": -6.35282039642334,
        "9": -32.4420166015625,
        "10": -111.36073303222656
      },
      "region_income_change": {
        "EAST_MIDLANDS": 0.0,
        "EAST_OF_ENGLAND": -10.243400573730469,
        "LONDON": 0.0,
        "NORTHERN_IRELAND": -46.37866973876953,
        "NORTH_EAST": -31.05316925048828,
        "NORTH_WEST": -56.40082550048828,
        "SCOTLAND": -48.145992279052734,
        "SOUTH_EAST": -2.8395535945892334,
        "SOUTH_WEST": 0.0,
        "WALES": -32.411991119384766,
        "WEST_MIDLANDS": -42.073150634765625,
        "YORKSHIRE": -41.130889892578125
      },
      "age_band_displacement_share": {
        "16-24": 0.05564074590802193,
        "25-34": 0.18047253787517548,
        "35-44": 0.12486308813095093,
        "45-54": 0.21555310487747192,
        "55-64": 0.19095604121685028,
        "65-+": 0.23251447081565857
      }
    },
    {
      "scenario": "full_tariff_reallocation_lag3",
      "tariff_scenario": "full_tariff",
      "margin": "reallocation",
      "exchequer_cost": 415219712.0,
      "poverty_rate_change_bhc": 7.239588665183816e-05,
      "poverty_rate_change_ahc": 0.0001533762095829727,
      "absolute_poverty_rate_change_bhc": NaN,
      "gini_baseline": 0.30908967456288927,
      "gini_shocked": 0.30916181018352173,
      "displaced_weighted": 0.0,
      "inactive_weighted": 0.0,
      "lcwra_weighted": 0.0,
      "reallocated_weighted": 34142.39453125,
      "gross_earnings_loss": 782674718.8714187,
      "net_disposable_loss": 484573184.0,
      "cushioning_rate": 0.3808753849891402,
      "decile_income_change": {
        "1": 0.0,
        "2": 0.0,
        "3": -4.830837726593018,
        "4": -6.239573001861572,
        "5": -66.33635711669922,
        "6": -19.85052490234375,
        "7": -37.99379348754883,
        "8": -39.0171012878418,
        "9": -31.394145965576172,
        "10": -31.864553451538086
      },
      "region_income_change": {
        "EAST_MIDLANDS": -24.421161651611328,
        "EAST_OF_ENGLAND": -67.17283630371094,
        "LONDON": -4.036240577697754,
        "NORTHERN_IRELAND": -22.7983455657959,
        "NORTH_EAST": -2.876579761505127,
        "NORTH_WEST": -3.565551519393921,
        "SCOTLAND": 0.0,
        "SOUTH_EAST": -41.67190933227539,
        "SOUTH_WEST": -21.203956604003906,
        "WALES": 0.0,
        "WEST_MIDLANDS": -36.30128479003906,
        "YORKSHIRE": -43.848262786865234
      },
      "age_band_displacement_share": {
        "16-24": 0.05232454836368561,
        "25-34": 0.11527983099222183,
        "35-44": 0.4919455051422119,
        "45-54": 0.20586317777633667,
        "55-64": 0.134586900472641,
        "65-+": 0.0
      }
    },
    {
      "scenario": "full_tariff_reallocation_lag3",
      "tariff_scenario": "full_tariff",
      "margin": "reallocation",
      "exchequer_cost": 399032320.0,
      "poverty_rate_change_bhc": 2.5721075069540245e-05,
      "poverty_rate_change_ahc": 5.363254904053316e-05,
      "absolute_poverty_rate_change_bhc": NaN,
      "gini_baseline": 0.30908967456288927,
      "gini_shocked": 0.30907149680277035,
      "displaced_weighted": 0.0,
      "inactive_weighted": 0.0,
      "lcwra_weighted": 0.0,
      "reallocated_weighted": 36445.51171875,
      "gross_earnings_loss": 829379368.2069018,
      "net_disposable_loss": 550371328.0,
      "cushioning_rate": 0.33640581246928103,
      "decile_income_change": {
        "1": 0.0,
        "2": 0.0,
        "3": -2.3541102409362793,
        "4": 0.0,
        "5": -13.715873718261719,
        "6": -21.659364700317383,
        "7": -54.43251419067383,
        "8": -37.087589263916016,
        "9": -17.502925872802734,
        "10": -80.5472183227539
      },
      "region_income_change": {
        "EAST_MIDLANDS": 0.0,
        "EAST_OF_ENGLAND": -67.4708023071289,
        "LONDON": -5.159762382507324,
        "NORTHERN_IRELAND": -8.426753997802734,
        "NORTH_EAST": 0.0,
        "NORTH_WEST": -16.40355110168457,
        "SCOTLAND": -43.53618240356445,
        "SOUTH_EAST": -28.63850975036621,
        "SOUTH_WEST": 0.0,
        "WALES": 0.0,
        "WEST_MIDLANDS": -62.20941925048828,
        "YORKSHIRE": -11.691972732543945
      },
      "age_band_displacement_share": {
        "16-24": 0.13185198605060577,
        "25-34": 0.1799822598695755,
        "35-44": 0.35191968083381653,
        "45-54": 0.24508990347385406,
        "55-64": 0.054427433758974075,
        "65-+": 0.03672880679368973
      }
    },
    {
      "scenario": "full_tariff_reallocation_lag3",
      "tariff_scenario": "full_tariff",
      "margin": "reallocation",
      "exchequer_cost": 454819840.0,
      "poverty_rate_change_bhc": 2.1662395209676166e-05,
      "poverty_rate_change_ahc": 0.00010734562805297942,
      "absolute_poverty_rate_change_bhc": NaN,
      "gini_baseline": 0.30908967456288927,
      "gini_shocked": 0.3090413887879927,
      "displaced_weighted": 0.0,
      "inactive_weighted": 0.0,
      "lcwra_weighted": 0.0,
      "reallocated_weighted": 35899.55859375,
      "gross_earnings_loss": 901654464.3288677,
      "net_disposable_loss": 582090752.0,
      "cushioning_rate": 0.35441926477537034,
      "decile_income_change": {
        "1": 0.0,
        "2": -1.6478383541107178,
        "3": 0.0,
        "4": -5.322477340698242,
        "5": -20.635255813598633,
        "6": -28.985116958618164,
        "7": -28.846540451049805,
        "8": 0.0,
        "9": -60.11661911010742,
        "10": -87.75255584716797
      },
      "region_income_change": {
        "EAST_MIDLANDS": 0.0,
        "EAST_OF_ENGLAND": 0.0,
        "LONDON": -34.549800872802734,
        "NORTHERN_IRELAND": -35.55276107788086,
        "NORTH_EAST": 0.0,
        "NORTH_WEST": -31.147933959960938,
        "SCOTLAND": -36.21236801147461,
        "SOUTH_EAST": -19.81938934326172,
        "SOUTH_WEST": -44.05271911621094,
        "WALES": 0.0,
        "WEST_MIDLANDS": -15.771265983581543,
        "YORKSHIRE": -39.210350036621094
      },
      "age_band_displacement_share": {
        "16-24": 0.04446885362267494,
        "25-34": 0.07403965294361115,
        "35-44": 0.3652134835720062,
        "45-54": 0.36580491065979004,
        "55-64": 0.15047314763069153,
        "65-+": 0.0
      }
    },
    {
      "scenario": "full_tariff_reallocation_lag3",
      "tariff_scenario": "full_tariff",
      "margin": "reallocation",
      "exchequer_cost": 380190720.0,
      "poverty_rate_change_bhc": 0.00015352115653183285,
      "poverty_rate_change_ahc": 0.00013451622900478855,
      "absolute_poverty_rate_change_bhc": NaN,
      "gini_baseline": 0.30908967456288927,
      "gini_shocked": 0.30912528141579676,
      "displaced_weighted": 0.0,
      "inactive_weighted": 0.0,
      "lcwra_weighted": 0.0,
      "reallocated_weighted": 28796.080078125,
      "gross_earnings_loss": 726148215.2233686,
      "net_disposable_loss": 454819840.0,
      "cushioning_rate": 0.3736542616715046,
      "decile_income_change": {
        "1": 0.0,
        "2": -12.816587448120117,
        "3": -0.2803574502468109,
        "4": -1.8087557554244995,
        "5": -18.040271759033203,
        "6": -31.031896591186523,
        "7": -2.710210084915161,
        "8": -123.63866424560547,
        "9": -1.4390684366226196,
        "10": -42.2299919128418
      },
      "region_income_change": {
        "EAST_MIDLANDS": -25.866336822509766,
        "EAST_OF_ENGLAND": -4.575706481933594,
        "LONDON": -65.82275390625,
        "NORTHERN_IRELAND": -35.50725173950195,
        "NORTH_EAST": 0.0,
        "NORTH_WEST": 0.0,
        "SCOTLAND": -5.053167819976807,
        "SOUTH_EAST": -16.51211166381836,
        "SOUTH_WEST": -28.60922622680664,
        "WALES": -46.55624771118164,
        "WEST_MIDLANDS": -26.004783630371094,
        "YORKSHIRE": -27.202577590942383
      },
      "age_band_displacement_share": {
        "16-24": 0.0,
        "25-34": 0.3844182789325714,
        "35-44": 0.33199915289878845,
        "45-54": 0.18639841675758362,
        "55-64": 0.055754516273736954,
        "65-+": 0.041429679840803146
      }
    },
    {
      "scenario": "full_tariff_reallocation_lag3",
      "tariff_scenario": "full_tariff",
      "margin": "reallocation",
      "exchequer_cost": 449544192.0,
      "poverty_rate_change_bhc": 5.3310429152853e-05,
      "poverty_rate_change_ahc": 0.00037673240277105724,
      "absolute_poverty_rate_change_bhc": NaN,
      "gini_baseline": 0.30908967456288927,
      "gini_shocked": 0.30921354999890727,
      "displaced_weighted": 0.0,
      "inactive_weighted": 0.0,
      "lcwra_weighted": 0.0,
      "reallocated_weighted": 35294.96484375,
      "gross_earnings_loss": 848767280.2947159,
      "net_disposable_loss": 526516224.0,
      "cushioning_rate": 0.37966950868183946,
      "decile_income_change": {
        "1": 0.0,
        "2": 0.0,
        "3": 0.0,
        "4": -30.664838790893555,
        "5": -28.055280685424805,
        "6": -53.32561492919922,
        "7": -65.3463134765625,
        "8": -44.2916259765625,
        "9": -6.440968990325928,
        "10": -30.072168350219727
      },
      "region_income_change": {
        "EAST_MIDLANDS": 0.0,
        "EAST_OF_ENGLAND": -22.105607986450195,
        "LONDON": -20.647960662841797,
        "NORTHERN_IRELAND": -67.14530944824219,
        "NORTH_EAST": -7.336244106292725,
        "NORTH_WEST": -11.678337097167969,
        "SCOTLAND": -11.517511367797852,
        "SOUTH_EAST": -14.02709674835205,
        "SOUTH_WEST": -9.366779327392578,
        "WALES": -30.400489807128906,
        "WEST_MIDLANDS": -81.96849060058594,
        "YORKSHIRE": -69.1961669921875
      },
      "age_band_displacement_share": {
        "16-24": 0.0,
        "25-34": 0.2061300426721573,
        "35-44": 0.1710684597492218,
        "45-54": 0.30461186170578003,
        "55-64": 0.3181896209716797,
        "65-+": 0.0
      }
    },
    {
      "scenario": "full_tariff_reallocation_lag3",
      "tariff_scenario": "full_tariff",
      "margin": "reallocation",
      "exchequer_cost": 464961536.0,
      "poverty_rate_change_bhc": 0.0,
      "poverty_rate_change_ahc": 3.925000534293899e-05,
      "absolute_poverty_rate_change_bhc": NaN,
      "gini_baseline": 0.30908967456288927,
      "gini_shocked": 0.3091098032347177,
      "displaced_weighted": 0.0,
      "inactive_weighted": 0.0,
      "lcwra_weighted": 0.0,
      "reallocated_weighted": 34340.5546875,
      "gross_earnings_loss": 876816332.4841832,
      "net_disposable_loss": 539361280.0,
      "cushioning_rate": 0.38486401311448026,
      "decile_income_change": {
        "1": -9.492891311645508,
        "2": 0.0,
        "3": 0.0,
        "4": -12.141691207885742,
        "5": -30.33639907836914,
        "6": -26.84427833557129,
        "7": -34.626590728759766,
        "8": 0.0,
        "9": -63.392208099365234,
        "10": -48.851680755615234
      },
      "region_income_change": {
        "EAST_MIDLANDS": -24.421161651611328,
        "EAST_OF_ENGLAND": -68.03546905517578,
        "LONDON": -9.584228515625,
        "NORTHERN_IRELAND": -4.2202959060668945,
        "NORTH_EAST": -6.229905605316162,
        "NORTH_WEST": -1.593056082725525,
        "SCOTLAND": 0.0,
        "SOUTH_EAST": -35.01274871826172,
        "SOUTH_WEST": -32.767539978027344,
        "WALES": -35.802772521972656,
        "WEST_MIDLANDS": -7.634552001953125,
        "YORKSHIRE": -33.05839157104492
      },
      "age_band_displacement_share": {
        "16-24": 0.03880351036787033,
        "25-34": 0.1301301270723343,
        "35-44": 0.4569864571094513,
        "45-54": 0.23962198197841644,
        "55-64": 0.06759700924158096,
        "65-+": 0.06686097383499146
      }
    },
    {
      "scenario": "full_tariff_reallocation_lag3",
      "tariff_scenario": "full_tariff",
      "margin": "reallocation",
      "exchequer_cost": 604110848.0,
      "poverty_rate_change_bhc": 3.9459382880996374e-05,
      "poverty_rate_change_ahc": 3.9459382880996374e-05,
      "absolute_poverty_rate_change_bhc": NaN,
      "gini_baseline": 0.30908967456288927,
      "gini_shocked": 0.3090990211805066,
      "displaced_weighted": 0.0,
      "inactive_weighted": 0.0,
      "lcwra_weighted": 0.0,
      "reallocated_weighted": 39961.8671875,
      "gross_earnings_loss": 1014800256.8415608,
      "net_disposable_loss": 563740672.0,
      "cushioning_rate": 0.4444811496652824,
      "decile_income_change": {
        "1": 0.0,
        "2": 0.0,
        "3": -5.359299182891846,
        "4": -5.006529331207275,
        "5": -11.443923950195312,
        "6": -60.613746643066406,
        "7": -30.137250900268555,
        "8": -69.15665435791016,
        "9": -76.97586822509766,
        "10": -30.27091407775879
      },
      "region_income_change": {
        "EAST_MIDLANDS": -17.584840774536133,
        "EAST_OF_ENGLAND": -39.23762893676758,
        "LONDON": -55.37957000732422,
        "NORTHERN_IRELAND": -3.7943098545074463,
        "NORTH_EAST": -106.25128936767578,
        "NORTH_WEST": -13.112397193908691,
        "SCOTLAND": -35.567298889160156,
        "SOUTH_EAST": -6.660757064819336,
        "SOUTH_WEST": -32.627689361572266,
        "WALES": -14.025548934936523,
        "WEST_MIDLANDS": 0.0,
        "YORKSHIRE": -40.106693267822266
      },
      "age_band_displacement_share": {
        "16-24": 0.03774730861186981,
        "25-34": 0.08080757409334183,
        "35-44": 0.41514450311660767,
        "45-54": 0.30111825466156006,
        "55-64": 0.16518241167068481,
        "65-+": 0.0
      }
    },
    {
      "scenario": "full_tariff_reallocation_lag3",
      "tariff_scenario": "full_tariff",
      "margin": "reallocation",
      "exchequer_cost": 347766784.0,
      "poverty_rate_change_bhc": 6.975452418578332e-05,
      "poverty_rate_change_ahc": 8.834069858129623e-05,
      "absolute_poverty_rate_change_bhc": NaN,
      "gini_baseline": 0.30908967456288927,
      "gini_shocked": 0.30910726118575793,
      "displaced_weighted": 0.0,
      "inactive_weighted": 0.0,
      "lcwra_weighted": 0.0,
      "reallocated_weighted": 28018.603515625,
      "gross_earnings_loss": 666068488.5885885,
      "net_disposable_loss": 417595392.0,
      "cushioning_rate": 0.37304436532511487,
      "decile_income_change": {
        "1": -27.033090591430664,
        "2": -3.8505053520202637,
        "3": -3.678382635116577,
        "4": 0.0,
        "5": -2.8466219902038574,
        "6": -31.384559631347656,
        "7": -19.865461349487305,
        "8": -3.837087869644165,
        "9": -64.53271484375,
        "10": -87.43659210205078
      },
      "region_income_change": {
        "EAST_MIDLANDS": -23.157432556152344,
        "EAST_OF_ENGLAND": -5.6102681159973145,
        "LONDON": -17.64215660095215,
        "NORTHERN_IRELAND": -34.438262939453125,
        "NORTH_EAST": -6.229905605316162,
        "NORTH_WEST": -12.660636901855469,
        "SCOTLAND": -16.0416259765625,
        "SOUTH_EAST": -27.95704460144043,
        "SOUTH_WEST": -19.065370559692383,
        "WALES": -47.21641540527344,
        "WEST_MIDLANDS": 0.0,
        "YORKSHIRE": -97.73878479003906
      },
      "age_band_displacement_share": {
        "16-24": 0.15678562223911285,
        "25-34": 0.030527187511324883,
        "35-44": 0.27770358324050903,
        "45-54": 0.3108649253845215,
        "55-64": 0.11593835055828094,
        "65-+": 0.10818026959896088
      }
    },
    {
      "scenario": "full_tariff_reallocation_lag3",
      "tariff_scenario": "full_tariff",
      "margin": "reallocation",
      "exchequer_cost": 478478336.0,
      "poverty_rate_change_bhc": 4.276108450512739e-05,
      "poverty_rate_change_ahc": 9.549170252723393e-05,
      "absolute_poverty_rate_change_bhc": NaN,
      "gini_baseline": 0.30908967456288927,
      "gini_shocked": 0.3091574448846379,
      "displaced_weighted": 0.0,
      "inactive_weighted": 0.0,
      "lcwra_weighted": 0.0,
      "reallocated_weighted": 37611.23046875,
      "gross_earnings_loss": 847354961.8082442,
      "net_disposable_loss": 494141440.0,
      "cushioning_rate": 0.41684245414045995,
      "decile_income_change": {
        "1": -9.492891311645508,
        "2": -2.5872440338134766,
        "3": -4.408416748046875,
        "4": -2.457689046859741,
        "5": -46.75359344482422,
        "6": -18.69622039794922,
        "7": -52.5955924987793,
        "8": -52.81382751464844,
        "9": -71.05596923828125,
        "10": -7.245867729187012
      },
      "region_income_change": {
        "EAST_MIDLANDS": -5.6742143630981445,
        "EAST_OF_ENGLAND": -15.185883522033691,
        "LONDON": -50.18828201293945,
        "NORTHERN_IRELAND": -21.562177658081055,
        "NORTH_EAST": -2.876579761505127,
        "NORTH_WEST": 0.0,
        "SCOTLAND": -31.19674301147461,
        "SOUTH_EAST": -89.16795349121094,
        "SOUTH_WEST": -6.045146942138672,
        "WALES": -14.093770980834961,
        "WEST_MIDLANDS": -11.123116493225098,
        "YORKSHIRE": -11.646201133728027
      },
      "age_band_displacement_share": {
        "16-24": 0.0,
        "25-34": 0.22953684628009796,
        "35-44": 0.17026424407958984,
        "45-54": 0.13843713700771332,
        "55-64": 0.41321465373039246,
        "65-+": 0.04854707792401314
      }
    },
    {
      "scenario": "full_tariff_reallocation_lag3",
      "tariff_scenario": "full_tariff",
      "margin": "reallocation",
      "exchequer_cost": 862027776.0,
      "poverty_rate_change_bhc": 2.5721075069540245e-05,
      "poverty_rate_change_ahc": 0.0,
      "absolute_poverty_rate_change_bhc": NaN,
      "gini_baseline": 0.30908967456288927,
      "gini_shocked": 0.30881183290235614,
      "displaced_weighted": 0.0,
      "inactive_weighted": 0.0,
      "lcwra_weighted": 0.0,
      "reallocated_weighted": 37115.828125,
      "gross_earnings_loss": 1536555499.745604,
      "net_disposable_loss": 897056768.0,
      "cushioning_rate": 0.41618980365595715,
      "decile_income_change": {
        "1": -3.002636194229126,
        "2": 0.0,
        "3": -2.3541102409362793,
        "4": -6.9289703369140625,
        "5": -9.2869234085083,
        "6": -40.35401916503906,
        "7": -32.42041015625,
        "8": -13.124503135681152,
        "9": -39.00272750854492,
        "10": -252.47364807128906
      },
      "region_income_change": {
        "EAST_MIDLANDS": -5.6742143630981445,
        "EAST_OF_ENGLAND": -39.7600212097168,
        "LONDON": -22.797300338745117,
        "NORTHERN_IRELAND": -21.870922088623047,
        "NORTH_EAST": 0.0,
        "NORTH_WEST": -10.101961135864258,
        "SCOTLAND": -15.221545219421387,
        "SOUTH_EAST": -2.994248390197754,
        "SOUTH_WEST": -51.8892707824707,
        "WALES": -454.879638671875,
        "WEST_MIDLANDS": -2.8533153533935547,
        "YORKSHIRE": -29.984798431396484
      },
      "age_band_displacement_share": {
        "16-24": 0.08863827586174011,
        "25-34": 0.2193620204925537,
        "35-44": 0.2610388994216919,
        "45-54": 0.180681511759758,
        "55-64": 0.140284925699234,
        "65-+": 0.10999426990747452
      }
    },
    {
      "scenario": "full_tariff_reallocation_lag3",
      "tariff_scenario": "full_tariff",
      "margin": "reallocation",
      "exchequer_cost": 404094976.0,
      "poverty_rate_change_bhc": 0.0002042385408128622,
      "poverty_rate_change_ahc": 4.7737800599939595e-05,
      "absolute_poverty_rate_change_bhc": NaN,
      "gini_baseline": 0.30908967456288927,
      "gini_shocked": 0.30903182746674607,
      "displaced_weighted": 0.0,
      "inactive_weighted": 0.0,
      "lcwra_weighted": 0.0,
      "reallocated_weighted": 29143.876953125,
      "gross_earnings_loss": 833124246.9699715,
      "net_disposable_loss": 502136832.0,
      "cushioning_rate": 0.39728457810915374,
      "decile_income_change": {
        "1": -3.002636194229126,
        "2": 0.0,
        "3": -19.924951553344727,
        "4": 0.0,
        "5": -6.0384626388549805,
        "6": -11.8065767288208,
        "7": 0.0,
        "8": -25.929370880126953,
        "9": -49.39419174194336,
        "10": -66.3764877319336
      },
      "region_income_change": {
        "EAST_MIDLANDS": -19.77070426940918,
        "EAST_OF_ENGLAND": -9.869195938110352,
        "LONDON": 0.0,
        "NORTHERN_IRELAND": -25.44383430480957,
        "NORTH_EAST": -28.17658805847168,
        "NORTH_WEST": -58.13188934326172,
        "SCOTLAND": 0.0,
        "SOUTH_EAST": -28.909521102905273,
        "SOUTH_WEST": -3.3987855911254883,
        "WALES": -5.051582336425781,
        "WEST_MIDLANDS": -18.60956382751465,
        "YORKSHIRE": -17.907512664794922
      },
      "age_band_displacement_share": {
        "16-24": 0.0,
        "25-34": 0.18035799264907837,
        "35-44": 0.19808505475521088,
        "45-54": 0.37629222869873047,
        "55-64": 0.19034898281097412,
        "65-+": 0.05491569638252258
      }
    }
  ]
}